terminatex/__init__.py
terminatex/core.py
terminatex-1.2.0.dist-info/METADATA
terminatex-1.2.0.dist-info/WHEEL
terminatex-1.2.0.dist-info/top_level.txt
terminatex-1.2.0.dist-info/RECORD
