Metadata-Version: 2.4
Name: terminatex
Version: 1.2.0
Summary: Displays clear, colorful LaTeX expressions directly in the terminal.
Author-email: Jose <bukitjose15@gmail.com>
Project-URL: Homepage, https://github.com/x0root/Terminatex
Classifier: Programming Language :: Python :: 3
Classifier: License :: OSI Approved :: MIT License
Classifier: Environment :: Console
Classifier: Topic :: Scientific/Engineering :: Mathematics
Classifier: Topic :: Terminals
Classifier: Operating System :: OS Independent
Requires-Python: >=3.8
Requires-Dist: matplotlib
Requires-Dist: Pillow
Requires-Dist: term-image
